wildblue/__init__.py
wildblue/_version.py
wildblue-0.0.1.dist-info/METADATA
wildblue-0.0.1.dist-info/RECORD
wildblue-0.0.1.dist-info/WHEEL
wildblue-0.0.1.dist-info/top_level.txt
